remapSDK/__init__.py
remapSDK/remapSDK.py
remapSDK/demo/__init__.py
remapSDK/demo/test_remapSDK.py
remapSDK/demo/testing_env.py
remapSDK/demo/data/aircraft_type.csv
remapSDK/demo/data/dataset.csv
remapSDK/demo/data/matrix.csv
remapSDK/demo/data/metadata.json
remapSDK/demo/data/sdk_config.json
remapSDK/demo/data/secret
remapSDK/demo/data/skills.csv
remapSDK/demo/data/slots.csv
remapSDK/demo/data/tasks.csv
remapSDK/demo/data/workforce.csv
remapSDK/demo/data/workpackages.csv
remapSDK-1.0.1.dist-info/LICENSE
remapSDK-1.0.1.dist-info/METADATA
remapSDK-1.0.1.dist-info/WHEEL
remapSDK-1.0.1.dist-info/top_level.txt
remapSDK-1.0.1.dist-info/RECORD
