Metadata-Version: 2.1
Name: remapSDK
Version: 1.0.1
Summary: ReMAP SDK for RUL, HealthIndicator and Planner models
Home-page: https://h2020-remap.eu/
Author: ATOS Mobility Unit
Author-email: alejandro.garcia@atos.net
License: UNKNOWN
Platform: UNKNOWN
Classifier: Programming Language :: Python :: 3
Classifier: License :: OSI Approved :: MIT License
Classifier: Operating System :: OS Independent
Requires-Python: >=3.8.5
Requires-Dist: flask
Requires-Dist: requests
